gptpy/__init__.py
gptpy/gptpy.py
gptpy/test.py
gptpy-0.1.6.dist-info/METADATA
gptpy-0.1.6.dist-info/WHEEL
gptpy-0.1.6.dist-info/entry_points.txt
gptpy-0.1.6.dist-info/top_level.txt
gptpy-0.1.6.dist-info/RECORD
